get_pbq
