Metadata-Version: 1.0
Name: get-pbq
Version: 0.2.3
Summary: Getting per base quality score from fastq/fastq.gz
Home-page: UNKNOWN
Author: Semar Petrus
Author-email: UNKNOWN
License: UNKNOWN
Platform: UNKNOWN
